avrora/__init__.py
avrora/py.typed
avrora-0.0.0.dist-info/LICENSE
avrora-0.0.0.dist-info/METADATA
avrora-0.0.0.dist-info/WHEEL
avrora-0.0.0.dist-info/RECORD
